deepdive/__init__.py
deepdive/nn.py
deepdive/tensor.py
deepdive/utils.py
deepdive_ml-1.0.0.dist-info/METADATA
deepdive_ml-1.0.0.dist-info/WHEEL
deepdive_ml-1.0.0.dist-info/top_level.txt
deepdive_ml-1.0.0.dist-info/RECORD
