Metadata-Version: 2.1
Name: deepdive-ml
Version: 1.0.0
Summary: A deep learning library from scratch in python
Author-email: Minhal Valiya Peedikakkal <minhaalvp@gmail.com>
Classifier: Intended Audience :: Developers
Classifier: Programming Language :: Python :: 3
Classifier: Programming Language :: Python :: 3.6
Classifier: Programming Language :: Python :: 3.7
Classifier: Programming Language :: Python :: 3.8
Requires-Dist: numpy
